setup.py
i3weather/__init__.py
i3weather/log.py
i3weather/main.py
i3weather.egg-info/PKG-INFO
i3weather.egg-info/SOURCES.txt
i3weather.egg-info/dependency_links.txt
i3weather.egg-info/entry_points.txt
i3weather.egg-info/requires.txt
i3weather.egg-info/top_level.txt