Metadata-Version: 1.1
Name: i3weather
Version: 1.1.0
Summary: Adds OpenWeatherMap data to i3status
Home-page: https://github.com/arosenfeld/i3weather
Author: Aaron Rosenfeld
Author-email: aaron@rosenfeld.io
License: UNKNOWN
Platform: UNKNOWN
Classifier: Development Status :: 4 - Beta
Classifier: License :: OSI Approved :: MIT License
Classifier: Operating System :: POSIX :: Linux
Classifier: Programming Language :: Python :: 3
